napari_napari/__init__.py
napari_napari/_widget.py
napari_napari/napari.yaml
napari_napari/_tests/__init__.py
napari_napari/_tests/test_widget.py
napari_napari-0.0.1.dist-info/LICENSE
napari_napari-0.0.1.dist-info/METADATA
napari_napari-0.0.1.dist-info/WHEEL
napari_napari-0.0.1.dist-info/entry_points.txt
napari_napari-0.0.1.dist-info/top_level.txt
napari_napari-0.0.1.dist-info/RECORD
