Metadata-Version: 2.1
Name: napari-napari
Version: 0.0.1
Summary: A napari viewer of the napari viewer
Home-page: https://github.com/jookuma/napari-napari
Author: Jordao Bragantini
Author-email: jordao.bragantini@gmail.com
License: BSD-3-Clause
Project-URL: Bug Tracker, https://github.com/jookuma/napari-napari/issues
Project-URL: Documentation, https://github.com/jookuma/napari-napari#README.md
Project-URL: Source Code, https://github.com/jookuma/napari-napari
Project-URL: User Support, https://github.com/jookuma/napari-napari/issues
Classifier: Development Status :: 2 - Pre-Alpha
Classifier: Framework :: napari
Classifier: Intended Audience :: Developers
Classifier: License :: OSI Approved :: BSD License
Classifier: Operating System :: OS Independent
Classifier: Programming Language :: Python
Classifier: Programming Language :: Python :: 3
Classifier: Programming Language :: Python :: 3 :: Only
Classifier: Programming Language :: Python :: 3.8
Classifier: Programming Language :: Python :: 3.9
Classifier: Programming Language :: Python :: 3.10
Classifier: Topic :: Scientific/Engineering :: Image Processing
Requires-Python: >=3.8
License-File: LICENSE
Requires-Dist: numpy
Requires-Dist: magicgui
Requires-Dist: qtpy
Provides-Extra: testing
Requires-Dist: tox ; extra == 'testing'
Requires-Dist: pytest ; extra == 'testing'
Requires-Dist: pytest-cov ; extra == 'testing'
Requires-Dist: pytest-qt ; extra == 'testing'
Requires-Dist: napari ; extra == 'testing'
Requires-Dist: pyqt5 ; extra == 'testing'
